test_project/__init__.py
test_project/setup.py
test_project/src/__init__.py
test_project/src/Request/EnrollDeviceRequest.py
test_project/src/Request/__init__.py
test_project/src/network/APIRequest.py
test_project/src/network/__init__.py
test_project/src/utils/APIConstants.py
test_project/src/utils/BaseHeader.py
test_project/src/utils/Config.py
test_project/src/utils/Constants.py
test_project/src/utils/Payloads.py
test_project/src/utils/__init__.py
test_project/tests/__init__.py
test_project/tests/test_demo.py
test_project/tests/test_ott_apis.py
test_project/tests/test_vma_apis.py
api_richa-0.0.1.dist-info/METADATA
api_richa-0.0.1.dist-info/WHEEL
api_richa-0.0.1.dist-info/top_level.txt
api_richa-0.0.1.dist-info/RECORD
