Metadata-Version: 2.1
Name: api-richa
Version: 0.0.1
Summary: API wrapper for request libray for pytest framework
Author: Richa
Author-email: richa.hope@in.verizon.com
Requires-Dist: pytest
Requires-Dist: requests
Requires-Dist: setuptools
Requires-Dist: wheel
Requires-Dist: twine
